sphinxcontrib/__init__.py
sphinxcontrib/jsontable/__init__.py
sphinxcontrib/jsontable/excel_data_loader.py
sphinxcontrib/jsontable/core/__init__.py
sphinxcontrib/jsontable/core/data_conversion_types.py
sphinxcontrib/jsontable/core/data_converter.py
sphinxcontrib/jsontable/core/data_converter_core.py
sphinxcontrib/jsontable/core/excel_reader.py
sphinxcontrib/jsontable/core/excel_reader_core.py
sphinxcontrib/jsontable/core/excel_reader_interface.py
sphinxcontrib/jsontable/core/excel_reader_mock.py
sphinxcontrib/jsontable/core/excel_workbook_info.py
sphinxcontrib/jsontable/core/header_detection.py
sphinxcontrib/jsontable/core/range_parser.py
sphinxcontrib/jsontable/directives/__init__.py
sphinxcontrib/jsontable/directives/backward_compatibility.py
sphinxcontrib/jsontable/directives/base_directive.py
sphinxcontrib/jsontable/directives/directive_core.py
sphinxcontrib/jsontable/directives/excel_processor.py
sphinxcontrib/jsontable/directives/json_processor.py
sphinxcontrib/jsontable/directives/table_builder.py
sphinxcontrib/jsontable/directives/table_converter.py
sphinxcontrib/jsontable/directives/validators.py
sphinxcontrib/jsontable/errors/__init__.py
sphinxcontrib/jsontable/errors/error_handler_core.py
sphinxcontrib/jsontable/errors/error_handlers.py
sphinxcontrib/jsontable/errors/error_types.py
sphinxcontrib/jsontable/errors/excel_errors.py
sphinxcontrib/jsontable/facade/excel_data_loader_facade.py
sphinxcontrib/jsontable/facade/excel_processing_pipeline.py
sphinxcontrib/jsontable/facade/excel_utilities.py
sphinxcontrib/jsontable/security/__init__.py
sphinxcontrib/jsontable/security/security_scanner.py
sphinxcontrib_jsontable-0.4.0.dist-info/licenses/LICENSE
sphinxcontrib_jsontable-0.4.0.dist-info/METADATA
sphinxcontrib_jsontable-0.4.0.dist-info/WHEEL
sphinxcontrib_jsontable-0.4.0.dist-info/top_level.txt
sphinxcontrib_jsontable-0.4.0.dist-info/RECORD
