Metadata-Version: 2.4
Name: sphinxcontrib-jsontable
Version: 0.4.0
Summary: Sphinx extension to render JSON and Excel data as tables with advanced processing features
Home-page: https://github.com/sasakama-code/sphinxcontrib-jsontable
Author: sasakama-code
Author-email: sasakama-code <sasakamacode@gmail.com>
Maintainer-email: sasakama-code <sasakamacode@gmail.com>
License-Expression: MIT
Project-URL: Homepage, https://github.com/sasakama-code/sphinxcontrib-jsontable
Project-URL: Repository, https://github.com/sasakama-code/sphinxcontrib-jsontable.git
Project-URL: Issues, https://github.com/sasakama-code/sphinxcontrib-jsontable/issues
Project-URL: Changelog, https://github.com/sasakama-code/sphinxcontrib-jsontable/blob/main/CHANGELOG.md
Project-URL: Documentation, https://github.com/sasakama-code/sphinxcontrib-jsontable#readme
Keywords: sphinx,json,table,documentation,rst,markdown
Classifier: Development Status :: 4 - Beta
Classifier: Environment :: Console
Classifier: Environment :: Web Environment
Classifier: Framework :: Sphinx :: Extension
Classifier: Intended Audience :: Developers
Classifier: Operating System :: OS Independent
Classifier: Programming Language :: Python
Classifier: Programming Language :: Python :: 3
Classifier: Programming Language :: Python :: 3.10
Classifier: Programming Language :: Python :: 3.11
Classifier: Programming Language :: Python :: 3.12
Classifier: Topic :: Documentation
Classifier: Topic :: Documentation :: Sphinx
Classifier: Topic :: Software Development :: Documentation
Classifier: Topic :: Text Processing :: Markup
Classifier: Topic :: Software Development :: Libraries :: Python Modules
Requires-Python: >=3.10
License-File: LICENSE
Requires-Dist: sphinx>=3.0
Requires-Dist: docutils>=0.18
Provides-Extra: excel
Requires-Dist: pandas>=2.0.0; extra == "excel"
Requires-Dist: openpyxl>=3.1.0; extra == "excel"
Requires-Dist: xlsxwriter>=3.0.0; extra == "excel"
Provides-Extra: dev
Requires-Dist: pytest>=8.3.5; extra == "dev"
Requires-Dist: pytest-cov>=5.0.0; extra == "dev"
Requires-Dist: pytest-benchmark>=5.1.0; extra == "dev"
Requires-Dist: coverage>=7.6.1; extra == "dev"
Requires-Dist: mypy>=1.14.1; extra == "dev"
Requires-Dist: ruff>=0.11.11; extra == "dev"
Requires-Dist: pre-commit>=3.5.0; extra == "dev"
Requires-Dist: build>=1.2.2.post1; extra == "dev"
Requires-Dist: twine>=6.1.0; extra == "dev"
Requires-Dist: safety>=3.5.2; extra == "dev"
Requires-Dist: pytest-mock>=3.10.0; extra == "dev"
Requires-Dist: pytest-xdist>=3.2.0; extra == "dev"
Provides-Extra: docs
Requires-Dist: sphinx-rtd-theme>=3.0.2; extra == "docs"
Requires-Dist: sphinx-autodoc-typehints>=2.0.1; extra == "docs"
Requires-Dist: myst-parser>=0.18; extra == "docs"
Provides-Extra: test
Requires-Dist: pytest>=8.3.5; extra == "test"
Requires-Dist: pytest-cov>=5.0.0; extra == "test"
Requires-Dist: pytest-mock>=3.10.0; extra == "test"
Requires-Dist: pytest-benchmark>=5.1.0; extra == "test"
Requires-Dist: pandas>=2.0.0; extra == "test"
Requires-Dist: openpyxl>=3.1.0; extra == "test"
Requires-Dist: psutil; extra == "test"
Provides-Extra: all
Requires-Dist: sphinxcontrib-jsontable[dev,docs,excel,test]; extra == "all"
Dynamic: author
Dynamic: home-page
Dynamic: license-file
Dynamic: requires-python
